picsl_greedy.cpython-312-darwin.so
picsl_greedy.dylibs/libvtkFiltersModeling-9.3.dylib
picsl_greedy.dylibs/libvtkIOLegacy-9.3.dylib
picsl_greedy.dylibs/libvtkverdict-9.3.dylib
picsl_greedy.dylibs/libvtkzlib-9.3.dylib
picsl_greedy.dylibs/libvtkexpat-9.3.dylib
picsl_greedy.dylibs/libvtkFiltersCore-9.3.dylib
picsl_greedy.dylibs/libvtkCommonMath-9.3.dylib
picsl_greedy.dylibs/libvtkDICOMParser-9.3.dylib
picsl_greedy.dylibs/libvtkFiltersSources-9.3.dylib
picsl_greedy.dylibs/libvtkIOXML-9.3.dylib
picsl_greedy.dylibs/libvtkloguru-9.3.dylib
picsl_greedy.dylibs/libvtkImagingSources-9.3.dylib
picsl_greedy.dylibs/libvtkIOPLY-9.3.dylib
picsl_greedy.dylibs/libvtkIOCore-9.3.dylib
picsl_greedy.dylibs/libvtkCommonColor-9.3.dylib
picsl_greedy.dylibs/libvtkRenderingCore-9.3.dylib
picsl_greedy.dylibs/libvtkmetaio-9.3.dylib
picsl_greedy.dylibs/libvtkpng-9.3.dylib
picsl_greedy.dylibs/libvtkFiltersGeometry-9.3.dylib
picsl_greedy.dylibs/libvtkCommonSystem-9.3.dylib
picsl_greedy.dylibs/libvtktiff-9.3.dylib
picsl_greedy.dylibs/libvtkIOGeometry-9.3.dylib
picsl_greedy.dylibs/libvtkkissfft-9.3.dylib
picsl_greedy.dylibs/libvtkImagingCore-9.3.dylib
picsl_greedy.dylibs/libvtkdoubleconversion-9.3.dylib
picsl_greedy.dylibs/libvtkpugixml-9.3.dylib
picsl_greedy.dylibs/libvtkfmt-9.3.dylib
picsl_greedy.dylibs/libvtkCommonComputationalGeometry-9.3.dylib
picsl_greedy.dylibs/libvtkCommonTransforms-9.3.dylib
picsl_greedy.dylibs/libvtkCommonCore-9.3.dylib
picsl_greedy.dylibs/libvtkjpeg-9.3.dylib
picsl_greedy.dylibs/libvtkCommonMisc-9.3.dylib
picsl_greedy.dylibs/libvtkFiltersGeneral-9.3.dylib
picsl_greedy.dylibs/libvtkFiltersHybrid-9.3.dylib
picsl_greedy.dylibs/libvtklz4-9.3.dylib
picsl_greedy.dylibs/libvtkCommonDataModel-9.3.dylib
picsl_greedy.dylibs/libvtkIOImage-9.3.dylib
picsl_greedy.dylibs/libvtkIOXMLParser-9.3.dylib
picsl_greedy.dylibs/libvtkCommonExecutionModel-9.3.dylib
picsl_greedy.dylibs/libvtksys-9.3.dylib
picsl_greedy.dylibs/libvtklzma-9.3.dylib
picsl_greedy-0.0.11.dist-info/RECORD
picsl_greedy-0.0.11.dist-info/WHEEL
picsl_greedy-0.0.11.dist-info/METADATA
picsl_greedy-0.0.11.dist-info/licenses/LICENSE
