Metadata-Version: 2.2
Name: picsl_greedy
Version: 0.0.11
Summary: Greedy: Fast Deformable Registration for 2D and 3D Medical Images
Author-Email: "Paul A. Yushkevich" <pyushkevich@gmail.com>
Maintainer-Email: "Paul A. Yushkevich" <pyushkevich@gmail.com>
License:                     GNU GENERAL PUBLIC LICENSE
Classifier: Development Status :: 4 - Beta
Classifier: License :: OSI Approved :: BSD License
Classifier: Programming Language :: Python :: 3 :: Only
Classifier: Programming Language :: Python :: 3.8
Classifier: Programming Language :: Python :: 3.9
Classifier: Programming Language :: Python :: 3.10
Classifier: Programming Language :: Python :: 3.11
Classifier: Programming Language :: Python :: 3.12
Classifier: Topic :: Scientific/Engineering :: Physics
Project-URL: Homepage, https://github.com/pyushkevich/greedy
Project-URL: Documentation, https://greedy.readthedocs.io/en/latest/
Requires-Python: >=3.8
Requires-Dist: typing_extensions
Requires-Dist: SimpleITK
Requires-Dist: numpy
